ansar/command/ansar_command.py
ansar/encode/__init__.py
ansar/encode/args.py
ansar/encode/codec.py
ansar/encode/command.py
ansar/encode/convert.py
ansar/encode/file.py
ansar/encode/folder.py
ansar/encode/json.py
ansar/encode/message.py
ansar/encode/portable.py
ansar/encode/primitive.py
ansar/encode/procedure.py
ansar/encode/release.py
ansar/encode/runtime.py
ansar/encode/support.py
ansar/encode/version.py
ansar/encode/xml.py
ansar_encode-1.0.8.dist-info/LICENSE
ansar_encode-1.0.8.dist-info/METADATA
ansar_encode-1.0.8.dist-info/WHEEL
ansar_encode-1.0.8.dist-info/entry_points.txt
ansar_encode-1.0.8.dist-info/top_level.txt
ansar_encode-1.0.8.dist-info/RECORD
