Metadata-Version: 2.1
Name: ansar-encode
Version: 1.0.8
Summary: Persistence of complex application data
Author: Scott Woods
Author-email: Scott Woods <ansar.library.management@gmail.com>
Project-URL: Documentation, http://ansar-encode-manual.s3-website-ap-southeast-2.amazonaws.com/0.1.1/index.html
Classifier: Development Status :: 5 - Production/Stable
Classifier: Intended Audience :: Developers
Classifier: Programming Language :: Python :: 3
Classifier: Programming Language :: Python :: 3.7
Classifier: Programming Language :: Python :: 3.8
Classifier: Programming Language :: Python :: 3.9
Classifier: Programming Language :: Python :: 3.10
Classifier: Programming Language :: Python :: 3.11
Classifier: Programming Language :: Python :: 3.12
Classifier: License :: OSI Approved :: MIT License
Classifier: Operating System :: OS Independent
Classifier: Topic :: Communications
Classifier: Topic :: File Formats
Classifier: Topic :: File Formats :: JSON
Classifier: Topic :: Software Development
Classifier: Topic :: Software Development :: Libraries
Classifier: Topic :: System
Classifier: Topic :: System :: Networking
Requires-Python: >=3.6
License-File: LICENSE
Requires-Dist: defusedxml>=0.7.1
Requires-Dist: python-dateutil>=2.8.1
